{
	"$id": "http://platform.selfkey.org/schema/attribute/tax-certificate.json",
	"$schema": "http://platform.selfkey.org/schema/identity-attribute.json",
	"identityAttribute": true,
	"identityAttributeRepository": "http://platform.selfkey.org/repository.json",
	"title": "Tax Certificate",
	"description": "Please provide a copy of a recent tax certificate. No older than 12 months.",
	"type": "object",
	"properties": {
		"image": {
			"$ref": "http://platform.selfkey.org/schema/file/image.json"
		},
		"issued": {
			"$ref": "http://platform.selfkey.org/schema/misc/issue-date.json"
		},
		"extra": {
			"$ref": "http://platform.selfkey.org/schema/misc/extra-images.json"
		}
	},
	"required": ["image", "issued"]
}
